constructROM/__init__.py
constructROM/conserv_laws.py
constructROM/construct_rhs_functions.py
constructROM/construct_roms.py
constructROM/display_odes.py
constructROM/hk_modes.py
construct_roms-1.0.dist-info/LICENSE
construct_roms-1.0.dist-info/METADATA
construct_roms-1.0.dist-info/WHEEL
construct_roms-1.0.dist-info/top_level.txt
construct_roms-1.0.dist-info/RECORD
