Metadata-Version: 2.1
Name: construct-roms
Version: 1.0
Summary: A Python package to build reduced-order models for Rayleigh-Benard convection
Home-page: https://github.com/PeriodicROM/construct_roms/
Author: Matt Olson
Author-email: mlolson@umich.edu
License: UNKNOWN
Platform: UNKNOWN
Classifier: Programming Language :: Python :: 3.7
Classifier: License :: OSI Approved :: MIT License
Requires-Dist: ipython (>=6)
Requires-Dist: numpy
Requires-Dist: sympy
